iFeatureOmegaCLI/__init__.py
iFeatureOmegaCLI/iFeatureOmegaCLI.py
iFeatureOmegaCLI/chem/AtomProperty.py
iFeatureOmegaCLI/chem/AtomTypes.py
iFeatureOmegaCLI/chem/__init__.py
iFeatureOmegaCLI/chem/autocor.py
iFeatureOmegaCLI/chem/basak.py
iFeatureOmegaCLI/chem/burden.py
iFeatureOmegaCLI/chem/cats.py
iFeatureOmegaCLI/chem/charge.py
iFeatureOmegaCLI/chem/connectivity.py
iFeatureOmegaCLI/chem/constitution.py
iFeatureOmegaCLI/chem/estate.py
iFeatureOmegaCLI/chem/fingerprint.py
iFeatureOmegaCLI/chem/fingerprint_old.py
iFeatureOmegaCLI/chem/kappa.py
iFeatureOmegaCLI/chem/property.py
iFeatureOmegaCLI/chem/topology.py
iFeatureOmegaCLI/data/AAidx.txt
iFeatureOmegaCLI/data/AAindex.data
iFeatureOmegaCLI/data/AAindex.txt
iFeatureOmegaCLI/data/CTD.txt
iFeatureOmegaCLI/data/DPCP.data
iFeatureOmegaCLI/data/DPCP.txt
iFeatureOmegaCLI/data/Grantham.txt
iFeatureOmegaCLI/data/PAAC.txt
iFeatureOmegaCLI/data/PCPsD.data
iFeatureOmegaCLI/data/PCPsD.txt
iFeatureOmegaCLI/data/Schneider-Wrede.txt
iFeatureOmegaCLI/data/TPCP.data
iFeatureOmegaCLI/data/TPCP.txt
iFeatureOmegaCLI/data/blosum62.txt
iFeatureOmegaCLI/data/diRNAPhyche.txt
iFeatureOmegaCLI/data/didnaPhyche.data
iFeatureOmegaCLI/data/didnaPhyche.txt
iFeatureOmegaCLI/data/dirnaPhyche.data
iFeatureOmegaCLI/data/triDNAPhyche.txt
iFeatureOmegaCLI/data/tridnaPhyche.data
iFeatureOmegaCLI/data_examples/1iir.pdb
iFeatureOmegaCLI/data_examples/Chemical_SMILES.txt
iFeatureOmegaCLI/data_examples/DNA_sequences.txt
iFeatureOmegaCLI/data_examples/RNA_sequences.txt
iFeatureOmegaCLI/data_examples/data_with_labels.csv
iFeatureOmegaCLI/data_examples/data_without_labels.csv
iFeatureOmegaCLI/data_examples/peptide_sample_label.txt
iFeatureOmegaCLI/data_examples/peptide_sequences.txt
iFeatureOmegaCLI/parameters/DNA_parameters_setting.json
iFeatureOmegaCLI/parameters/Protein_parameters_setting.json
iFeatureOmegaCLI/parameters/RNA_parameters_setting.json
iFeatureOmegaCLI/parameters/Structure_parameters_setting.json
iFeatureOmegaCLI/util/CheckAccPseParameter.py
iFeatureOmegaCLI-1.0.2.dist-info/METADATA
iFeatureOmegaCLI-1.0.2.dist-info/WHEEL
iFeatureOmegaCLI-1.0.2.dist-info/top_level.txt
iFeatureOmegaCLI-1.0.2.dist-info/RECORD
